{
    "BART": {
      "hf_path": "facebook/bart-large-cnn",
      "task": "summarization",
      "token_limit": 1024
    },
    "DISTILBART": {
      "hf_path": "sshleifer/distilbart-cnn-12-6",
      "task": "summarization",
      "token_limit": 1024
    },
    "T5": {
      "hf_path": "google-t5/t5-small",
      "task": "translation",
      "token_limit": 512
    },
    "LEGAL-BART-BILLSUM": {
      "hf_path": "local_models/legal-bart-billsum",
      "task": "summarization",
      "token_limit": 1024
    },
    "LEGAL-LED-MULTILEXSUM": {
      "hf_path": "local_models/legal-led-multilexsum",
      "task": "summarization",
      "token_limit": 16384
    },
    "DEBUG-TEST": {
      "hf_path": "local_models/nonexisting",
      "task": "summarization",
      "token_limit": 1024
    }
  }